deduce/__init__.py
deduce/ingest.py
Deduce_Ingest-1.1.dist-info/METADATA
Deduce_Ingest-1.1.dist-info/WHEEL
Deduce_Ingest-1.1.dist-info/top_level.txt
Deduce_Ingest-1.1.dist-info/RECORD
