Metadata-Version: 2.1
Name: Deduce-Ingest
Version: 1.1
Summary: Deduce data ingestion
Home-page: http://github.com/deduce-com/python-deduce-ingest
Author: Deduce
Author-email: support@deduce.com
License: MIT
Platform: UNKNOWN
